StORF_Reporter/StORF_Extractor.py
StORF_Reporter/StORF_Finder.py
StORF_Reporter/StORF_Remover.py
StORF_Reporter/StORF_Reporter.py
StORF_Reporter/UR_Extractor.py
StORF_Reporter/__init__.py
StORF_Reporter/constants.py
StORF_Reporter/utils.py
StORF_Reporter/Tools/StORF_Adder.py
StORF_Reporter/Tools/UR_Lenghts.py
StORF_Reporter/Tools/Un_StORFed.py
StORF_Reporter/Tools/__init__.py
storf_reporter-1.4.7.dist-info/licenses/LICENSE
storf_reporter-1.4.7.dist-info/METADATA
storf_reporter-1.4.7.dist-info/WHEEL
storf_reporter-1.4.7.dist-info/entry_points.txt
storf_reporter-1.4.7.dist-info/top_level.txt
storf_reporter-1.4.7.dist-info/RECORD
