Metadata-Version: 2.4
Name: StORF-Reporter
Version: 1.4.7
Summary: StORF-Reporter - A a tool that takes an annotated genome and returns missing CDS genes (Stop-to-Stop) from unannotated regions.
Home-page: https://github.com/NickJD/StORF-Reporter
Author: Nicholas Dimonaco
Author-email: nicholas@dimonaco.co.uk
Project-URL: Bug Tracker, https://github.com/NickJD/StORF-Reporter/issues
Classifier: Programming Language :: Python :: 3
Classifier: License :: OSI Approved :: GNU General Public License v3 (GPLv3)
Classifier: Operating System :: OS Independent
Requires-Python: >=3.9
License-File: LICENSE
Requires-Dist: numpy
Requires-Dist: pyrodigal
Dynamic: license-file
